pyowencloud/__init__.py
pyowencloud/pyowencloud.py
pyowencloud/examples/__init__.py
pyowencloud/examples/example_devices.py
pyowencloud/examples/example_last_value.py
pyowencloud/examples/example_parameters.py
pyowencloud/examples/example_value.py
pyowencloud-0.3.dist-info/METADATA
pyowencloud-0.3.dist-info/RECORD
pyowencloud-0.3.dist-info/WHEEL
pyowencloud-0.3.dist-info/top_level.txt
